[{"rawversion": "1.19.1-42.0.9", "mcversion": "1.19.1", "version": "42.0.9"}, {"rawversion": "1.19.1-42.0.8", "mcversion": "1.19.1", "version": "42.0.8"}, {"rawversion": "1.19.1-42.0.5", "mcversion": "1.19.1", "version": "42.0.5"}, {"rawversion": "1.19.1-42.0.4", "mcversion": "1.19.1", "version": "42.0.4"}, {"rawversion": "1.19.1-42.0.3", "mcversion": "1.19.1", "version": "42.0.3"}, {"rawversion": "1.19.1-42.0.2", "mcversion": "1.19.1", "version": "42.0.2"}, {"rawversion": "1.19.1-42.0.1", "mcversion": "1.19.1", "version": "42.0.1"}, {"rawversion": "1.19.1-42.0.0", "mcversion": "1.19.1", "version": "42.0.0"}]